ghostfolio_mcp/__init__.py
ghostfolio_mcp/ghostfolio_client.py
ghostfolio_mcp/ghostfolio_tools.py
ghostfolio_mcp/middlewares.py
ghostfolio_mcp/models.py
ghostfolio_mcp/sentry_init.py
ghostfolio_mcp/server.py
ghostfolio_mcp/utils.py
ghostfolio_mcp-1.1.0.dist-info/METADATA
ghostfolio_mcp-1.1.0.dist-info/WHEEL
ghostfolio_mcp-1.1.0.dist-info/entry_points.txt
ghostfolio_mcp-1.1.0.dist-info/licenses/LICENSE
ghostfolio_mcp-1.1.0.dist-info/RECORD
