Metadata-Version: 2.4
Name: ghostfolio-mcp
Version: 1.1.0
Summary: MCP server for Ghostfolio management
Project-URL: Homepage, https://github.com/mhajder/ghostfolio-mcp
Project-URL: Repository, https://github.com/mhajder/ghostfolio-mcp
Project-URL: Documentation, https://github.com/mhajder/ghostfolio-mcp#readme
Project-URL: Issues, https://github.com/mhajder/ghostfolio-mcp/issues
Author: Mateusz Hajder
License:                     GNU AFFERO GENERAL PUBLIC LICENSE
License-File: LICENSE
Keywords: ghostfolio,management,mcp
Classifier: Development Status :: 5 - Production/Stable
Classifier: Intended Audience :: Developers
Classifier: License :: OSI Approved :: GNU Affero General Public License v3 or later (AGPLv3+)
Classifier: Programming Language :: Python :: 3 :: Only
Classifier: Programming Language :: Python :: 3.11
Classifier: Programming Language :: Python :: 3.12
Classifier: Programming Language :: Python :: 3.13
Classifier: Topic :: Utilities
Requires-Python: >=3.11
Requires-Dist: fastmcp>=2.10.0
Requires-Dist: httpx>=0.27.0
Requires-Dist: pydantic>=2.0.0
Requires-Dist: python-dotenv>=1.0.0
Provides-Extra: sentry
Requires-Dist: sentry-sdk>=2.43.0; extra == 'sentry'
